tabpy_client/__init__.py
tabpy_client/client.py
tabpy_client/custom_query_object.py
tabpy_client/query_object.py
tabpy_client/rest.py
tabpy_client/rest_client.py
tabpy_client/schema.py
tabpy_client-0.2.dist-info/DESCRIPTION.rst
tabpy_client-0.2.dist-info/METADATA
tabpy_client-0.2.dist-info/RECORD
tabpy_client-0.2.dist-info/WHEEL
tabpy_client-0.2.dist-info/metadata.json
tabpy_client-0.2.dist-info/top_level.txt
