Metadata-Version: 1.1
Name: tabpy-client
Version: 0.2
Summary: Python client library to manage Tableau Python Server.
Home-page: https://github.com/tableau/TabPy
Author: Tableau
Author-email: github@tableau.com
License: MIT
Platform: UNKNOWN
Classifier: Development Status :: 3 - Alpha
Classifier: Intended Audience :: Developers
Classifier: Programming Language :: Python :: 2.7
Classifier: Programming Language :: Python :: 3.5
Classifier: Topic :: Scientific/Engineering
Classifier: Topic :: Scientific/Engineering :: Information Analysis
